LICENSE.txt
README.md
setup.py
Urlcut.py.egg-info/PKG-INFO
Urlcut.py.egg-info/SOURCES.txt
Urlcut.py.egg-info/dependency_links.txt
Urlcut.py.egg-info/requires.txt
Urlcut.py.egg-info/top_level.txt
urlcutpy/__init__.py