Metadata-Version: 2.1
Name: Urlcut.py
Version: 1.0.8
Summary: Official Urlcut Public API package.
Home-page: https://urlcut.app
Author: Urlcut
Author-email: support@urlcut.app
License: MIT
Keywords: urlcut
Classifier: Development Status :: 5 - Production/Stable
Classifier: Intended Audience :: Education
Classifier: Operating System :: Microsoft :: Windows :: Windows 10
Classifier: License :: OSI Approved :: MIT License
Classifier: Programming Language :: Python :: 3
License-File: LICENSE.txt
